<?xml version="1.0" encoding="utf-8"?>
<clothingItem>
	<m_MaleModel>Skinned\clothes\M_BonnieHat_Back</m_MaleModel>
	<m_FemaleModel>Skinned\clothes\F_BonnieHat_Back</m_FemaleModel>
	<m_GUID>d452b5a7-2bae-4db0-a6c0-8c60bc07f52d</m_GUID>
	<m_Static>true</m_Static>
	<m_AllowRandomHue>false</m_AllowRandomHue>
	<m_AllowRandomTint>false</m_AllowRandomTint>
	<m_HatCategory>default</m_HatCategory>
	<m_MasksFolder>media/textures/Clothes/Hat/Masks</m_MasksFolder>
	<textureChoices>Clothes/BonnieHat_UsmcDesertCamo</textureChoices>
</clothingItem>